danittr/__init__.py
danittr/__main__.py
danittr/config.py
danittr/font.py
danittr/fpsdisplay.py
danittr/gameloop.py
danittr/keymapping.py
danittr/logconfig.py
danittr/music.py
danittr/palette.py
danittr/sound.py
danittr/actor/__init__.py
danittr/actor/npc.py
danittr/actor/rocketscorpion.py
danittr/actor/thornshooter/__init__.py
danittr/actor/thornshooter/healthbar.py
danittr/actor/thornshooter/main.py
danittr/actor/thornshooter/thornbullet.py
danittr/appcommon/__init__.py
danittr/appcommon/autoblit.py
danittr/appcommon/collision.py
danittr/appcommon/dialog.py
danittr/appcommon/dialoguefactory.py
danittr/appcommon/exception.py
danittr/appcommon/gensurf.py
danittr/appcommon/loadscreen.py
danittr/appcommon/overrider.py
danittr/appcommon/promptfactory.py
danittr/appcommon/resources.py
danittr/appcommon/signfactory.py
danittr/appcommon/style.py
danittr/appcommon/surf.py
danittr/appcommon/task.py
danittr/appcommon/anim/__init__.py
danittr/appcommon/anim/node.py
danittr/appcommon/anim/player/__init__.py
danittr/appcommon/anim/player/main.py
danittr/appcommon/anim/player/utils.py
danittr/appcommon/anim/proc/__init__.py
danittr/appcommon/anim/proc/assist.py
danittr/appcommon/anim/proc/main.py
danittr/appcommon/behaviour/__init__.py
danittr/appcommon/behaviour/buffer.py
danittr/appcommon/behaviour/load.py
danittr/appcommon/behaviour/main.py
danittr/appcommon/behaviour/save.py
danittr/appcommon/behaviour/setting.py
danittr/appcommon/behaviour/switch.py
danittr/appcommon/text/__init__.py
danittr/appcommon/text/main.py
danittr/appcommon/text/label/__init__.py
danittr/appcommon/text/label/autolabel.py
danittr/appcommon/text/label/main.py
danittr/backprop/__init__.py
danittr/backprop/backprops.py
danittr/block/__init__.py
danittr/block/blocks.py
danittr/block/grassdirt.py
danittr/cloud/__init__.py
danittr/cloud/clouds.py
danittr/common/__init__.py
danittr/common/behaviour.py
danittr/common/indexgen.py
danittr/common/jsonhandler.py
danittr/common/math.py
danittr/common/pointgen.py
danittr-0.38.2.dist-info/METADATA
danittr-0.38.2.dist-info/WHEEL
danittr-0.38.2.dist-info/entry_points.txt
danittr-0.38.2.dist-info/top_level.txt
danittr-0.38.2.dist-info/RECORD
