Metadata-Version: 2.1
Name: danittr
Version: 0.38.2
Summary: A game prototype (platformer) made with pygame
Home-page: https://github.com/IndiePython/danittr
Author: Kennedy Richard
Author-email: kennedy@kennedyrichard.com
License: Unlicense
Project-URL: Source, https://github.com/IndiePython/danittr
Project-URL: Donate, https://indiepython.com/donate
Keywords: desktop,game,application,pygame,platformer,prototype
Classifier: License :: OSI Approved :: The Unlicense (Unlicense)
Classifier: Development Status :: 4 - Beta
Classifier: Programming Language :: Python :: 3
Classifier: Programming Language :: Python :: 3.6
Classifier: Programming Language :: Python :: 3.7
Classifier: Programming Language :: Python :: 3.8
Classifier: Programming Language :: Python :: 3.9
Classifier: Programming Language :: Python :: 3.10
Classifier: Programming Language :: Python :: Implementation :: CPython
Classifier: Topic :: Games/Entertainment
Classifier: Topic :: Software Development :: Libraries :: pygame
Classifier: Topic :: Multimedia
Requires-Python: >=3.6
Requires-Dist: pygame
